{
   "html_attributions" : [],
   "result" : {
      "address_components" : [
         {
            "long_name" : "San Pablo Tepetlapa",
            "short_name" : "San Pablo Tepetlapa",
            "types" : [ "sublocality_level_1", "sublocality", "political" ]
         },
         {
            "long_name" : "Ciudad de México",
            "short_name" : "México D.F.",
            "types" : [ "locality", "political" ]
         },
         {
            "long_name" : "Distrito Federal",
            "short_name" : "D.F.",
            "types" : [ "administrative_area_level_1", "political" ]
         },
         {
            "long_name" : "México",
            "short_name" : "MX",
            "types" : [ "country", "political" ]
         },
         {
            "long_name" : "04620",
            "short_name" : "04620",
            "types" : [ "postal_code" ]
         }
      ],
      "adr_address" : "Av. División del Norte 3572, \u003cspan class=\"street-address\"\u003eCoyoacán\u003c/span\u003e, \u003cspan class=\"extended-address\"\u003eSan Pablo Tepetlapa\u003c/span\u003e, \u003cspan class=\"postal-code\"\u003e04620\u003c/span\u003e \u003cspan class=\"locality\"\u003eCiudad de México\u003c/span\u003e, \u003cspan class=\"region\"\u003eD.F.\u003c/span\u003e, \u003cspan class=\"country-name\"\u003eMéxico\u003c/span\u003e",
      "formatted_address" : "Av. División del Norte 3572, Coyoacán, San Pablo Tepetlapa, 04620 Ciudad de México, D.F., México",
      "formatted_phone_number" : "01 55 5617 0411",
      "geometry" : {
         "location" : {
            "lat" : 19.3240391,
            "lng" : -99.13902499999999
         }
      },
      "icon" : "https://maps.gstatic.com/mapfiles/place_api/icons/museum-71.png",
      "id" : "3c6b3f816e31c229cdc436d608e649b10ee8ec72",
      "international_phone_number" : "+52 55 5617 0411",
      "name" : "Museo del Automóvil",
      "opening_hours" : {
         "open_now" : true,
         "periods" : [
            {
               "close" : {
                  "day" : 0,
                  "time" : "1800"
               },
               "open" : {
                  "day" : 0,
                  "time" : "1000"
               }
            },
            {
               "close" : {
                  "day" : 2,
                  "time" : "1800"
               },
               "open" : {
                  "day" : 2,
                  "time" : "1000"
               }
            },
            {
               "close" : {
                  "day" : 3,
                  "time" : "1800"
               },
               "open" : {
                  "day" : 3,
                  "time" : "1000"
               }
            },
            {
               "close" : {
                  "day" : 4,
                  "time" : "1800"
               },
               "open" : {
                  "day" : 4,
                  "time" : "1000"
               }
            },
            {
               "close" : {
                  "day" : 5,
                  "time" : "1800"
               },
               "open" : {
                  "day" : 5,
                  "time" : "1000"
               }
            },
            {
               "close" : {
                  "day" : 6,
                  "time" : "1800"
               },
               "open" : {
                  "day" : 6,
                  "time" : "1000"
               }
            }
         ],
         "weekday_text" : [
            "lunes: Cerrado",
            "martes: 10:00–18:00",
            "miércoles: 10:00–18:00",
            "jueves: 10:00–18:00",
            "viernes: 10:00–18:00",
            "sábado: 10:00–18:00",
            "domingo: 10:00–18:00"
         ]
      },
      "photos" : [
         {
            "height" : 2448,
            "html_attributions" : [
               "\u003ca href=\"https://maps.google.com/maps/contrib/113549153275973242466/photos\"\u003eJaime Navarrete\u003c/a\u003e"
            ],
            "photo_reference" : "CmRdAAAA9ygrOG-ghC0m-Ej32CGWdkhPyJMolhcr7gW6CX603xkeg-XSmLfwq3heKJeQO4kYsSZ0Y91711u7E0QxS7_-LhAXF4i1kZ8KvMRP-fI9yki4dDDgQ_31a8AfS_kOUyFCEhCStv0ApMjNrtr86YjFftUAGhSjT8yT0NanJb9N2zpGottRRoXc5g",
            "width" : 3264
         },
         {
            "height" : 2448,
            "html_attributions" : [
               "\u003ca href=\"https://maps.google.com/maps/contrib/100026596858905180029/photos\"\u003eKevin Josue Perez Beltran\u003c/a\u003e"
            ],
            "photo_reference" : "CmRdAAAAdDUc_aOuJoYCPESl_wSpY_zbVhJEqa1HFO-VJ18xJ_WSxYl8P65xYDlrpsBgiJ28AkZPW8jklI1yg5z2Joe2iUj4FZ9vfkSCiY_nfgWw0o-s0FhrbY9aUev2FLTomrk3EhDGgAw082T4V_NTHTtzdpoWGhQVxqMk1wuOA2XMJ1vUQundFcATlQ",
            "width" : 3264
         },
         {
            "height" : 1944,
            "html_attributions" : [
               "\u003ca href=\"https://maps.google.com/maps/contrib/117388765526354113171/photos\"\u003eFrancisco Castillo Muñoz\u003c/a\u003e"
            ],
            "photo_reference" : "CmRdAAAA3XWHGOZIbmnAFBEF1_qBShK9RYfO4QEO28HtQOscJWABbSlinjWsgdzeqWCuTSQEH4l8Lr7Dw61o2FkwoF-WoUclKv3JX4YeYpkne6PBSpB7uY769fk8PIdOUjGBmvGyEhBukeRYUE4iB8cFtlRJnpo-GhTkC88s9QZLud22oQpXEMEiHAtIEQ",
            "width" : 2592
         },
         {
            "height" : 2448,
            "html_attributions" : [
               "\u003ca href=\"https://maps.google.com/maps/contrib/113549153275973242466/photos\"\u003eJaime Navarrete\u003c/a\u003e"
            ],
            "photo_reference" : "CmRdAAAAhmiqBI6zydNG4f2ekVZK-UV93G4lkt0Lava_t8Ql3FsqwYXndTaWwt1C3a05JaGrD_-Igcg8V5D03a8vLdDgiBKJi9YbC3r56FjBmoy0t3ho_uLV2s2jbrRV3ZcGMP3-EhDYUK2xzOhdFIluUrL2la5rGhQCW_L45rPsLG1pP49WjWn2r4THVw",
            "width" : 3264
         },
         {
            "height" : 2448,
            "html_attributions" : [
               "\u003ca href=\"https://maps.google.com/maps/contrib/113549153275973242466/photos\"\u003eJaime Navarrete\u003c/a\u003e"
            ],
            "photo_reference" : "CmRdAAAA4DcLCRMjPElDBZWCgRkfHMCme6NSVMyxqzMUMniHh8nCqp5rfPKF8uyQBt4T8JeKv90j229iGxDshDqDVUBMMPXorgDHeHV3tS6h1TZP9xi0ApiEjOlPksdqREoPKsXxEhDiw6fIo0rIJs6Pjj-ZgHVHGhTIyB0LstC3oXJo7TAYxGkK1DdP1g",
            "width" : 3264
         },
         {
            "height" : 1944,
            "html_attributions" : [
               "\u003ca href=\"https://maps.google.com/maps/contrib/117388765526354113171/photos\"\u003eFrancisco Castillo Muñoz\u003c/a\u003e"
            ],
            "photo_reference" : "CoQBcwAAAEXxKQjNREhQurdjIXE3mXFUycaNvwkcxaESF0VKqqPVNH3anHaHGblQtGO1A4So82mX2uQCl3zV3-VTVOrxDZvne2VHK-k-VKIn0IcRGxzySC7eYQ0TuxfKaoAfVngXLpVP5scG4qBY2ZuZYbqceqQbw-xu4u1lrdFmwVK5hX62EhCIvd2BURV6Lk4rZb_bRvh9GhTdY_5Akkjir-g888QCwfVZJfmSpA",
            "width" : 2592
         },
         {
            "height" : 2304,
            "html_attributions" : [
               "\u003ca href=\"https://maps.google.com/maps/contrib/107650976207983372331/photos\"\u003eRafael Tovar\u003c/a\u003e"
            ],
            "photo_reference" : "CmRdAAAAWVTgeFOJIXKdAfsTp0q-48jzF38xFwmTXHpVN05Hr6v8yAtrHrUso79kSpJ9maCsc5GT0kMR2hRyMNebn_-Uii9MQN4FhphI2XSW1J4bD7BPa7hwFUnn4HmF-IRe_JllEhC-pUC1ZuJb9aR0y-MH9YlQGhTRJtZyOVBl_1qX4EqK1bAXdFz_yw",
            "width" : 4096
         },
         {
            "height" : 1456,
            "html_attributions" : [
               "\u003ca href=\"https://maps.google.com/maps/contrib/104738896473206412618/photos\"\u003eHector Marin Sanchez\u003c/a\u003e"
            ],
            "photo_reference" : "CmRdAAAARaedn0UmhhoFKkWQ34igVXAQ11YDS8DOS9nVUXgIZC-kpO6HL2Zi52gR2P2TGr2iFtNadBamobih4KqBa3xst_OkF4Be5ZV4cnKbEqfTD7Ng-P0W060rPxSBseFrdFCvEhB5TEITRbC5wj9SfWbjLr2oGhTsDBqXMeXdwvIY9hMfjm7wBAakjw",
            "width" : 2592
         },
         {
            "height" : 768,
            "html_attributions" : [
               "\u003ca href=\"https://maps.google.com/maps/contrib/104394343703139853889/photos\"\u003eOmar Alexis Hernandez Lopez\u003c/a\u003e"
            ],
            "photo_reference" : "CmRdAAAAgJWairNq5RxgukCE1PCYf2a5_Gjm0tO5L4HOUwDrdskMY6YhLJqRCEPSoodlJvPJ5PBbRzZ9PeLjCqNg9TuS61ixgZXK7LxuTeQcHZykm3xmQ3RQ8Hj1V3Q1X6w16pOGEhA6Qg0M1jzEucCyhlWNfSFNGhTPdXYdAsCkTssj7NFoRHx20x7upQ",
            "width" : 1024
         },
         {
            "height" : 1456,
            "html_attributions" : [
               "\u003ca href=\"https://maps.google.com/maps/contrib/104738896473206412618/photos\"\u003eHector Marin Sanchez\u003c/a\u003e"
            ],
            "photo_reference" : "CmRdAAAAjQo4S_jJ8JtpsuRowSNTioESXP1t9FqQKeE_VUDm07EiDrD0TTQdCIM44IkHzOww7ivans6icd2AbDNzWDZwdAPnbx3VW6yiOZBKJ4k_rrRsZL7piVVFwlsXVfXsC9P6EhCSJPg1Z7Ftd5Zoe2pUuiXcGhRQ731yTCZQrboWWssMeaguC4uCJg",
            "width" : 2592
         }
      ],
      "place_id" : "ChIJa3EzNs3-0YURZVzbJ0oY5hs",
      "rating" : 4.3,
      "reference" : "CnRnAAAAtipArdDes76mXWzUmmVqvIFyFJMDzrKWAhum2G8CIkSHvY1BnWkkaZgGSV44eTTjiCbbkOf8uR-QQ8cjpCB8nTPE9dkac6Kd8Zb8I7RzrCF_1OMGLkCfoVyzj755Z3eHYmzW1Rxwm6o2bcGwCHypuhIQ-sul1LxxwtNcu763FVa1sBoULMjnBzFFk-R-XV8r5tuM_joU6mQ",
      "reviews" : [
         {
            "aspects" : [
               {
                  "rating" : 2,
                  "type" : "overall"
               }
            ],
            "author_name" : "Felipe Javier Flores Gomez",
            "author_url" : "https://plus.google.com/109595949800446194938",
            "language" : "es",
            "profile_photo_url" : "//lh5.googleusercontent.com/-swQBDg9Y1SM/AAAAAAAAAAI/AAAAAAAEL-g/MA-K1uMrOp0/photo.jpg",
            "rating" : 4,
            "text" : "Excelente museo. ",
            "time" : 1448843677
         },
         {
            "aspects" : [
               {
                  "rating" : 2,
                  "type" : "overall"
               }
            ],
            "author_name" : "Francisco Castillo Muñoz",
            "author_url" : "https://plus.google.com/117388765526354113171",
            "language" : "es",
            "profile_photo_url" : "//lh3.googleusercontent.com/-zAY4_Pm-hTA/AAAAAAAAAAI/AAAAAAAAHmk/Cz9L-7y4BH8/photo.jpg",
            "rating" : 4,
            "text" : "Tiene aproximadamente 120 autos en exhibición. Los autos están en perfectas condiciones. Es un museo que hay que visitar.",
            "time" : 1454559343
         },
         {
            "aspects" : [
               {
                  "rating" : 3,
                  "type" : "overall"
               }
            ],
            "author_name" : "Kevin Josue Perez Beltran",
            "author_url" : "https://plus.google.com/100026596858905180029",
            "language" : "es",
            "profile_photo_url" : "//lh4.googleusercontent.com/-otWPDP251T0/AAAAAAAAAAI/AAAAAAAAD20/oxvqLqElvMw/photo.jpg",
            "rating" : 5,
            "text" : "Un buen sitio para visitar, no esta caro la entrada y los autos estan bien cuidados",
            "time" : 1454535806
         },
         {
            "aspects" : [
               {
                  "rating" : 2,
                  "type" : "overall"
               }
            ],
            "author_name" : "Abner Solis",
            "author_url" : "https://plus.google.com/107494341077681561787",
            "language" : "es",
            "profile_photo_url" : "//lh5.googleusercontent.com/-CE7-faTMCBo/AAAAAAAAAAI/AAAAAAAAAJo/bdhA2RSixQo/photo.jpg",
            "rating" : 4,
            "text" : "Esta muy bien cuidado y tienen bastantes carros pero me gustaría que fuera más dinámico ",
            "time" : 1450677392
         },
         {
            "aspects" : [
               {
                  "rating" : 1,
                  "type" : "overall"
               }
            ],
            "author_name" : "Yair Gittler",
            "author_url" : "https://plus.google.com/101602082467839521460",
            "language" : "es",
            "profile_photo_url" : "//lh4.googleusercontent.com/-TqWIxcpzjus/AAAAAAAAAAI/AAAAAAAAABs/byHixue19hA/photo.jpg",
            "rating" : 3,
            "text" : "Una muy buena opción si estás en Coyoacán y si eres amante de los coches. Si no te fascinan, la vas a pasar bien pero hasta ahí, nada fuera de este mundo.\n\n#GameChangers #adictosalaciudad",
            "time" : 1380516914
         }
      ],
      "scope" : "GOOGLE",
      "types" : [ "museum", "point_of_interest", "establishment" ],
      "url" : "https://maps.google.com/?cid=2010320990442839141",
      "user_ratings_total" : 46,
      "utc_offset" : -360,
      "vicinity" : "Av. División del Norte 3572, Coyoacán, San Pablo Tepetlapa, Ciudad de México",
      "website" : "http://www.museodelautomovil.com.mx/"
   },
   "status" : "OK"
}
